{
  "$schema": "https://json.schemastore.org/tsconfig",
  "compilerOptions": {
    "allowJs": true,
    "allowSyntheticDefaultImports": true,
    "allowUnreachableCode": false,
    "allowUnusedLabels": false,
    "checkJs": true,
    "composite": false,
    "declaration": false,
    "declarationMap": false,
    "diagnostics": true,
    "disableSizeLimit": true,
    "esModuleInterop": true,
    "exactOptionalPropertyTypes": true,
    "forceConsistentCasingInFileNames": true,
    "isolatedModules": true,
    "newLine": "lf",
    "noEmit": true,
    "noEmitOnError": true,
    "noErrorTruncation": true,
    "noFallthroughCasesInSwitch": true,
    "noPropertyAccessFromIndexSignature": true,
    "noUncheckedIndexedAccess": true,
    "noUnusedLocals": true,
    "noUnusedParameters": true,
    "preserveSymlinks": false,
    "removeComments": true,
    "resolveJsonModule": true,
    "skipLibCheck": true,
    "sourceMap": true,
    "strict": true
  },
  "display": "Base"
}
